dyffi_bus_client/__init__.py
dyffi_bus_client/client.py
dyffi_bus_client-0.1.4.dist-info/METADATA
dyffi_bus_client-0.1.4.dist-info/WHEEL
dyffi_bus_client-0.1.4.dist-info/top_level.txt
dyffi_bus_client-0.1.4.dist-info/RECORD
