Metadata-Version: 2.2
Name: dyffi-bus-client
Version: 0.1.4
Summary: A async Pub/Sub client for Dyffi-Bus
Author-email: Yehor Kochetov <yehor.kochetov@gmail.com>
License: MIT
Project-URL: Homepage, https://github.com/Ametion/Dyffi-Bus-Client
Project-URL: Repository, https://github.com/Ametion/Dyffi-Bus-Client
Requires-Python: >=3.6
Requires-Dist: requests
Requires-Dist: websocket-client
Requires-Dist: pycurl
